README.md
gplaycli.conf
setup.py
gplaycli/__init__.py
gplaycli/__main__.py
gplaycli/gplaycli.py
gplaycli/hooks.py
gplaycli/util.py
gplaycli.egg-info/PKG-INFO
gplaycli.egg-info/SOURCES.txt
gplaycli.egg-info/dependency_links.txt
gplaycli.egg-info/entry_points.txt
gplaycli.egg-info/requires.txt
gplaycli.egg-info/top_level.txt