Metadata-Version: 1.0
Name: gplaycli
Version: 3.27
Summary: GPlayCli, a Google play downloader command line interface
Home-page: https://github.com/matlink/gplaycli
Author: Matlink
Author-email: matlink@matlink.fr
License: AGPLv3
Platform: UNKNOWN
